[{"__symbolic":"module","version":4,"metadata":{"AuthenticationActionTypes":{"PROGRESSING_STARTED":"[AUTHENTICATION] PROGRESSING_STARTED","PROGRESSING_FINISHED":"[AUTHENTICATION] PROGRESSING_FINISHED","FAILED_HAPPENED":"[AUTHENTICATION] FAILED_HAPPENED"},"ProgressingStarted":{"__symbolic":"class"},"ProgressingFinished":{"__symbolic":"class"},"FailedHappened":{"__symbolic":"class","members":{"__ctor__":[{"__symbolic":"constructor","parameters":[{"__symbolic":"reference","name":"any"}]}]}},"AuthenticationAction":{"__symbolic":"interface"}}}]