[{"__symbolic":"module","version":4,"metadata":{"SigninEffects":{"__symbolic":"class","decorators":[{"__symbolic":"call","expression":{"__symbolic":"reference","module":"@angular/core","name":"Injectable","line":20,"character":1}}],"members":{"__ctor__":[{"__symbolic":"constructor","parameters":[{"__symbolic":"reference","module":"@ngrx/effects","name":"Actions","line":22,"character":31},{"__symbolic":"reference","module":"@angular/router","name":"Router","line":22,"character":56},{"__symbolic":"reference","module":"../services","name":"SigninService","line":22,"character":86}]}],"preSignUpStart$":[{"__symbolic":"property","decorators":[{"__symbolic":"call","expression":{"__symbolic":"reference","module":"@ngrx/effects","name":"Effect","line":24,"character":2}}]}],"SigninSucceed$":[{"__symbolic":"property","decorators":[{"__symbolic":"call","expression":{"__symbolic":"reference","module":"@ngrx/effects","name":"Effect","line":32,"character":2},"arguments":[{"dispatch":false}]}]}],"AfterSigninFiled$":[{"__symbolic":"property","decorators":[{"__symbolic":"call","expression":{"__symbolic":"reference","module":"@ngrx/effects","name":"Effect","line":38,"character":2}}]}],"redirectToLoginPage$":[{"__symbolic":"property","decorators":[{"__symbolic":"call","expression":{"__symbolic":"reference","module":"@ngrx/effects","name":"Effect","line":40,"character":2},"arguments":[{"dispatch":false}]}]}]}}}}]